co/__init__.py
co/logup/__init__.py
co/logup/clients/APIClient.py
co/logup/clients/LogupClient.py
co/logup/clients/__init__.py
co/logup/endpoints/Subscription.py
co/logup/endpoints/Verification.py
co/logup/endpoints/__init__.py
logup-1.0.0.dist-info/DESCRIPTION.rst
logup-1.0.0.dist-info/METADATA
logup-1.0.0.dist-info/RECORD
logup-1.0.0.dist-info/WHEEL
logup-1.0.0.dist-info/metadata.json
logup-1.0.0.dist-info/top_level.txt
