Metadata-Version: 2.0
Name: logup
Version: 1.0.0
Summary: The LogUp SDK for Python
Home-page: https://github.com/logupinc/logup-sdk-python
Author: LogUp Inc.
Author-email: it@logup.co
License: Apache License 2.0
Keywords: logup logup-sdk-python logup-python logup-sdk
Platform: UNKNOWN
Classifier: Development Status :: 5 - Production/Stable
Classifier: Natural Language :: English
Classifier: License :: OSI Approved :: Apache Software License
Classifier: Intended Audience :: Developers
Classifier: Topic :: Software Development :: Build Tools
Classifier: Programming Language :: Python :: 2.7
Requires-Dist: requests
